modbus_query/config.yaml
modbus_query/modbus_query.py
modbus_query-2.0.0.dist-info/LICENSE
modbus_query-2.0.0.dist-info/METADATA
modbus_query-2.0.0.dist-info/WHEEL
modbus_query-2.0.0.dist-info/entry_points.txt
modbus_query-2.0.0.dist-info/top_level.txt
modbus_query-2.0.0.dist-info/RECORD
