Metadata-Version: 2.1
Name: modbus-query
Version: 2.0.0
Summary: A program for querying Modbus register values.
Home-page: https://pypi.python.org/pypi/modbus-query/
Author: Brian Moran
License: BSD
Keywords: modbus,query,midmark
Platform: UNKNOWN
Classifier: Programming Language :: Python :: 3
Classifier: Topic :: Utilities
Classifier: License :: OSI Approved :: BSD License
License-File: LICENSE
Requires-Dist: minimalmodbus (==2.0.1)
Requires-Dist: platformdirs (==2.5.2)
Requires-Dist: PyYAML (==6.0)
